ad_map_access.libs/libboost_program_options-d4bd10da.so.1.72.0
ad_map_access.libs/libboost_filesystem-72663748.so.1.72.0
ad_map_access.libs/libpugixml-802c44cb.so.1.8
ad_map_access.libs/libad_map_access-062691d6.so
ad_map_access.libs/libad_map_opendrive_reader-09c58f67.so
ad_map_access.libs/libad_physics-8a865103.so
ad_map_access.libs/libproj-ee79edee.so.12.0.0
ad_map_access.libs/libboost_python36-9b56ac8c.so.1.72.0
ad_map_access/ad_map_access_python36.so
ad_map_access/__init__.py
ad_map_access-2.6.3.dist-info/top_level.txt
ad_map_access-2.6.3.dist-info/WHEEL
ad_map_access-2.6.3.dist-info/METADATA
ad_map_access-2.6.3.dist-info/RECORD
